pathaliases.py
pathaliases-0.0.3.dist-info/DESCRIPTION.rst
pathaliases-0.0.3.dist-info/METADATA
pathaliases-0.0.3.dist-info/RECORD
pathaliases-0.0.3.dist-info/WHEEL
pathaliases-0.0.3.dist-info/metadata.json
pathaliases-0.0.3.dist-info/top_level.txt
