Metadata-Version: 2.0
Name: pathaliases
Version: 0.0.3
Summary: A python package for handling path aliases.
Home-page: https://github.com/adamkewley/pathaliases
Author: Adam Kewley
Author-email: contact@adamkewley.com
License: Apache 2.0
Download-URL: https://github.com/adamkewley/pathaliases/tarball/0.0.3
Keywords: path aliasing
Platform: UNKNOWN
Classifier: Development Status :: 4 - Beta
Classifier: Intended Audience :: Developers
Classifier: Programming Language :: Python :: 3.4
Classifier: License :: OSI Approved :: Apache Software License
Requires-Dist: PyYAML (==3.12)
